{"config":{"output_file":null,"full_docs":false,"pub_only":false,"reachable_only":false,"distro_crate":false,"signatures":false,"borrow_data":false},"version":"0.19.0","compilation":{"directory":"c:\\Users\\ccc\\rust-project-euler\\euler22","program":"C:\\Users\\ccc\\.rustup\\toolchains\\stable-x86_64-pc-windows-msvc\\bin\\rls.exe","arguments":[],"output":"c:\\Users\\ccc\\rust-project-euler\\euler22\\target\\rls\\debug\\deps\\libeuler22-4cd37b4de8216ff0.rmeta"},"prelude":{"crate_id":{"name":"euler22","disambiguator":[8739401441100406612,10480811089268687714]},"crate_root":"src","external_crates":[{"file_name":"c:\\Users\\ccc\\rust-project-euler\\euler22\\src\\main.rs","num":1,"id":{"name":"std","disambiguator":[13454279496936976369,256594374343364064]}},{"file_name":"c:\\Users\\ccc\\rust-project-euler\\euler22\\src\\main.rs","num":2,"id":{"name":"core","disambiguator":[10635428080862470944,4053010167158610789]}},{"file_name":"c:\\Users\\ccc\\rust-project-euler\\euler22\\src\\main.rs","num":3,"id":{"name":"compiler_builtins","disambiguator":[2397070696586021034,1787692942867494326]}},{"file_name":"c:\\Users\\ccc\\rust-project-euler\\euler22\\src\\main.rs","num":4,"id":{"name":"rustc_std_workspace_core","disambiguator":[13215350897914660053,4762041400992555299]}},{"file_name":"c:\\Users\\ccc\\rust-project-euler\\euler22\\src\\main.rs","num":5,"id":{"name":"alloc","disambiguator":[8309206586370028958,10530789326598529563]}},{"file_name":"c:\\Users\\ccc\\rust-project-euler\\euler22\\src\\main.rs","num":6,"id":{"name":"libc","disambiguator":[12844497061290288730,1165546255938205329]}},{"file_name":"c:\\Users\\ccc\\rust-project-euler\\euler22\\src\\main.rs","num":7,"id":{"name":"unwind","disambiguator":[17370511097861102976,8088456066398622915]}},{"file_name":"c:\\Users\\ccc\\rust-project-euler\\euler22\\src\\main.rs","num":8,"id":{"name":"hashbrown","disambiguator":[1985867887572050615,3717448080532913995]}},{"file_name":"c:\\Users\\ccc\\rust-project-euler\\euler22\\src\\main.rs","num":9,"id":{"name":"rustc_std_workspace_alloc","disambiguator":[10045986561377339069,14963295625130836827]}},{"file_name":"c:\\Users\\ccc\\rust-project-euler\\euler22\\src\\main.rs","num":10,"id":{"name":"rustc_demangle","disambiguator":[14681916437073319406,9740076823699971540]}},{"file_name":"c:\\Users\\ccc\\rust-project-euler\\euler22\\src\\main.rs","num":11,"id":{"name":"panic_unwind","disambiguator":[4514194809136982995,14217700833302823945]}}],"span":{"file_name":"src\\main.rs","byte_start":0,"byte_end":801,"line_start":1,"line_end":32,"column_start":1,"column_end":2}},"imports":[],"defs":[{"kind":"Mod","id":{"krate":0,"index":0},"span":{"file_name":"src\\main.rs","byte_start":0,"byte_end":801,"line_start":1,"line_end":32,"column_start":1,"column_end":2},"name":"","qualname":"::","value":"src\\main.rs","parent":null,"children":[{"krate":0,"index":10},{"krate":0,"index":11},{"krate":0,"index":12},{"krate":0,"index":13},{"krate":0,"index":15},{"krate":0,"index":17}],"decl_id":null,"docs":"","sig":null,"attributes":[]},{"kind":"Function","id":{"krate":0,"index":12},"span":{"file_name":"src\\main.rs","byte_start":3,"byte_end":7,"line_start":1,"line_end":1,"column_start":4,"column_end":8},"name":"main","qualname":"::main","value":"fn () -> ()","parent":null,"children":[],"decl_id":null,"docs":"","sig":null,"attributes":[]},{"kind":"Local","id":{"krate":0,"index":4294967281},"span":{"file_name":"src\\main.rs","byte_start":20,"byte_end":24,"line_start":2,"line_end":2,"column_start":9,"column_end":13},"name":"data","qualname":"data$14","value":"std::string::String","parent":null,"children":[],"decl_id":null,"docs":"","sig":null,"attributes":[]},{"kind":"Local","id":{"krate":0,"index":4294967270},"span":{"file_name":"src\\main.rs","byte_start":99,"byte_end":104,"line_start":3,"line_end":3,"column_start":9,"column_end":14},"name":"data2","qualname":"data2$25","value":"std::string::String","parent":null,"children":[],"decl_id":null,"docs":"","sig":null,"attributes":[]},{"kind":"Local","id":{"krate":0,"index":4294967262},"span":{"file_name":"src\\main.rs","byte_start":140,"byte_end":145,"line_start":4,"line_end":4,"column_start":13,"column_end":18},"name":"names","qualname":"names$33","value":"std::vec::Vec<&str>","parent":null,"children":[],"decl_id":null,"docs":"","sig":null,"attributes":[]},{"kind":"Local","id":{"krate":0,"index":4294967244},"span":{"file_name":"src\\main.rs","byte_start":219,"byte_end":224,"line_start":8,"line_end":8,"column_start":13,"column_end":18},"name":"score","qualname":"score$51","value":"usize","parent":null,"children":[],"decl_id":null,"docs":"","sig":null,"attributes":[]},{"kind":"Local","id":{"krate":0,"index":4294967241},"span":{"file_name":"src\\main.rs","byte_start":239,"byte_end":240,"line_start":9,"line_end":9,"column_start":10,"column_end":11},"name":"i","qualname":"i$54","value":"usize","parent":null,"children":[],"decl_id":null,"docs":"","sig":null,"attributes":[]},{"kind":"Local","id":{"krate":0,"index":4294967240},"span":{"file_name":"src\\main.rs","byte_start":242,"byte_end":246,"line_start":9,"line_end":9,"column_start":13,"column_end":17},"name":"name","qualname":"name$55","value":"&&str","parent":null,"children":[],"decl_id":null,"docs":"","sig":null,"attributes":[]},{"kind":"Local","id":{"krate":0,"index":4294967231},"span":{"file_name":"src\\main.rs","byte_start":290,"byte_end":292,"line_start":10,"line_end":10,"column_start":13,"column_end":15},"name":"ws","qualname":"ws$64","value":"usize","parent":null,"children":[],"decl_id":null,"docs":"","sig":null,"attributes":[]},{"kind":"Local","id":{"krate":0,"index":4294967212},"span":{"file_name":"src\\main.rs","byte_start":445,"byte_end":446,"line_start":17,"line_end":17,"column_start":17,"column_end":18},"name":"s","qualname":"::remove_quote::s","value":"&str","parent":null,"children":[],"decl_id":null,"docs":"","sig":null,"attributes":[]},{"kind":"Function","id":{"krate":0,"index":13},"span":{"file_name":"src\\main.rs","byte_start":432,"byte_end":444,"line_start":17,"line_end":17,"column_start":4,"column_end":16},"name":"remove_quote","qualname":"::remove_quote","value":"fn (s: &str) -> String","parent":null,"children":[],"decl_id":null,"docs":"","sig":null,"attributes":[]},{"kind":"Local","id":{"krate":0,"index":4294967197},"span":{"file_name":"src\\main.rs","byte_start":488,"byte_end":489,"line_start":18,"line_end":18,"column_start":23,"column_end":24},"name":"c","qualname":"$105::c","value":"&char","parent":null,"children":[],"decl_id":null,"docs":"","sig":null,"attributes":[]},{"kind":"Local","id":{"krate":0,"index":4294967185},"span":{"file_name":"src\\main.rs","byte_start":532,"byte_end":534,"line_start":21,"line_end":21,"column_start":18,"column_end":20},"name":"ch","qualname":"::letter_number::ch","value":"char","parent":null,"children":[],"decl_id":null,"docs":"","sig":null,"attributes":[]},{"kind":"Function","id":{"krate":0,"index":15},"span":{"file_name":"src\\main.rs","byte_start":518,"byte_end":531,"line_start":21,"line_end":21,"column_start":4,"column_end":17},"name":"letter_number","qualname":"::letter_number","value":"fn (ch: char) -> usize","parent":null,"children":[],"decl_id":null,"docs":"","sig":null,"attributes":[]},{"kind":"Local","id":{"krate":0,"index":4294967177},"span":{"file_name":"src\\main.rs","byte_start":561,"byte_end":568,"line_start":22,"line_end":22,"column_start":9,"column_end":16},"name":"letters","qualname":"letters$118","value":"&str","parent":null,"children":[],"decl_id":null,"docs":"","sig":null,"attributes":[]},{"kind":"Local","id":{"krate":0,"index":4294967168},"span":{"file_name":"src\\main.rs","byte_start":631,"byte_end":632,"line_start":23,"line_end":23,"column_start":31,"column_end":32},"name":"c","qualname":"$134::c","value":"char","parent":null,"children":[],"decl_id":null,"docs":"","sig":null,"attributes":[]},{"kind":"Local","id":{"krate":0,"index":4294967154},"span":{"file_name":"src\\main.rs","byte_start":673,"byte_end":677,"line_start":26,"line_end":26,"column_start":15,"column_end":19},"name":"word","qualname":"::word_score::word","value":"&str","parent":null,"children":[],"decl_id":null,"docs":"","sig":null,"attributes":[]},{"kind":"Function","id":{"krate":0,"index":17},"span":{"file_name":"src\\main.rs","byte_start":662,"byte_end":672,"line_start":26,"line_end":26,"column_start":4,"column_end":14},"name":"word_score","qualname":"::word_score","value":"fn (word: &str) -> usize","parent":null,"children":[],"decl_id":null,"docs":"","sig":null,"attributes":[]},{"kind":"Local","id":{"krate":0,"index":4294967145},"span":{"file_name":"src\\main.rs","byte_start":708,"byte_end":713,"line_start":27,"line_end":27,"column_start":13,"column_end":18},"name":"score","qualname":"score$150","value":"usize","parent":null,"children":[],"decl_id":null,"docs":"","sig":null,"attributes":[]},{"kind":"Local","id":{"krate":0,"index":4294967143},"span":{"file_name":"src\\main.rs","byte_start":727,"byte_end":729,"line_start":28,"line_end":28,"column_start":9,"column_end":11},"name":"ch","qualname":"ch$152","value":"char","parent":null,"children":[],"decl_id":null,"docs":"","sig":null,"attributes":[]}],"impls":[],"refs":[{"kind":"Function","span":{"file_name":"src\\main.rs","byte_start":64,"byte_end":70,"line_start":2,"line_end":2,"column_start":53,"column_end":59},"ref_id":{"krate":2,"index":4593}},{"kind":"Function","span":{"file_name":"src\\main.rs","byte_start":36,"byte_end":50,"line_start":2,"line_end":2,"column_start":25,"column_end":39},"ref_id":{"krate":1,"index":2002}},{"kind":"Mod","span":{"file_name":"src\\main.rs","byte_start":27,"byte_end":30,"line_start":2,"line_end":2,"column_start":16,"column_end":19},"ref_id":{"krate":1,"index":0}},{"kind":"Mod","span":{"file_name":"src\\main.rs","byte_start":32,"byte_end":34,"line_start":2,"line_end":2,"column_start":21,"column_end":23},"ref_id":{"krate":1,"index":1970}},{"kind":"Function","span":{"file_name":"src\\main.rs","byte_start":107,"byte_end":119,"line_start":3,"line_end":3,"column_start":17,"column_end":29},"ref_id":{"krate":0,"index":13}},{"kind":"Variable","span":{"file_name":"src\\main.rs","byte_start":121,"byte_end":125,"line_start":3,"line_end":3,"column_start":31,"column_end":35},"ref_id":{"krate":0,"index":4294967281}},{"kind":"Type","span":{"file_name":"src\\main.rs","byte_start":147,"byte_end":150,"line_start":4,"line_end":4,"column_start":20,"column_end":23},"ref_id":{"krate":5,"index":3563}},{"kind":"Function","span":{"file_name":"src\\main.rs","byte_start":176,"byte_end":183,"line_start":4,"line_end":4,"column_start":49,"column_end":56},"ref_id":{"krate":2,"index":3188}},{"kind":"Function","span":{"file_name":"src\\main.rs","byte_start":165,"byte_end":170,"line_start":4,"line_end":4,"column_start":38,"column_end":43},"ref_id":{"krate":2,"index":6213}},{"kind":"Variable","span":{"file_name":"src\\main.rs","byte_start":159,"byte_end":164,"line_start":4,"line_end":4,"column_start":32,"column_end":37},"ref_id":{"krate":0,"index":4294967270}},{"kind":"Function","span":{"file_name":"src\\main.rs","byte_start":198,"byte_end":202,"line_start":6,"line_end":6,"column_start":11,"column_end":15},"ref_id":{"krate":5,"index":3077}},{"kind":"Variable","span":{"file_name":"src\\main.rs","byte_start":192,"byte_end":197,"line_start":6,"line_end":6,"column_start":5,"column_end":10},"ref_id":{"krate":0,"index":4294967262}},{"kind":"Function","span":{"file_name":"src\\main.rs","byte_start":264,"byte_end":273,"line_start":9,"line_end":9,"column_start":35,"column_end":44},"ref_id":{"krate":2,"index":3168}},{"kind":"Function","span":{"file_name":"src\\main.rs","byte_start":257,"byte_end":261,"line_start":9,"line_end":9,"column_start":28,"column_end":32},"ref_id":{"krate":2,"index":4933}},{"kind":"Variable","span":{"file_name":"src\\main.rs","byte_start":251,"byte_end":256,"line_start":9,"line_end":9,"column_start":22,"column_end":27},"ref_id":{"krate":0,"index":4294967262}},{"kind":"Function","span":{"file_name":"src\\main.rs","byte_start":295,"byte_end":305,"line_start":10,"line_end":10,"column_start":18,"column_end":28},"ref_id":{"krate":0,"index":17}},{"kind":"Variable","span":{"file_name":"src\\main.rs","byte_start":306,"byte_end":310,"line_start":10,"line_end":10,"column_start":29,"column_end":33},"ref_id":{"krate":0,"index":4294967240}},{"kind":"Variable","span":{"file_name":"src\\main.rs","byte_start":343,"byte_end":344,"line_start":11,"line_end":11,"column_start":31,"column_end":32},"ref_id":{"krate":0,"index":4294967241}},{"kind":"Variable","span":{"file_name":"src\\main.rs","byte_start":351,"byte_end":355,"line_start":11,"line_end":11,"column_start":39,"column_end":43},"ref_id":{"krate":0,"index":4294967240}},{"kind":"Variable","span":{"file_name":"src\\main.rs","byte_start":357,"byte_end":359,"line_start":11,"line_end":11,"column_start":45,"column_end":47},"ref_id":{"krate":0,"index":4294967231}},{"kind":"Variable","span":{"file_name":"src\\main.rs","byte_start":370,"byte_end":375,"line_start":12,"line_end":12,"column_start":9,"column_end":14},"ref_id":{"krate":0,"index":4294967244}},{"kind":"Variable","span":{"file_name":"src\\main.rs","byte_start":379,"byte_end":381,"line_start":12,"line_end":12,"column_start":18,"column_end":20},"ref_id":{"krate":0,"index":4294967231}},{"kind":"Variable","span":{"file_name":"src\\main.rs","byte_start":385,"byte_end":386,"line_start":12,"line_end":12,"column_start":24,"column_end":25},"ref_id":{"krate":0,"index":4294967241}},{"kind":"Variable","span":{"file_name":"src\\main.rs","byte_start":418,"byte_end":423,"line_start":14,"line_end":14,"column_start":20,"column_end":25},"ref_id":{"krate":0,"index":4294967244}},{"kind":"Type","span":{"file_name":"src\\main.rs","byte_start":457,"byte_end":463,"line_start":17,"line_end":17,"column_start":29,"column_end":35},"ref_id":{"krate":5,"index":4679}},{"kind":"Function","span":{"file_name":"src\\main.rs","byte_start":502,"byte_end":509,"line_start":18,"line_end":18,"column_start":37,"column_end":44},"ref_id":{"krate":2,"index":3188}},{"kind":"Function","span":{"file_name":"src\\main.rs","byte_start":480,"byte_end":486,"line_start":18,"line_end":18,"column_start":15,"column_end":21},"ref_id":{"krate":2,"index":3163}},{"kind":"Function","span":{"file_name":"src\\main.rs","byte_start":472,"byte_end":477,"line_start":18,"line_end":18,"column_start":7,"column_end":12},"ref_id":{"krate":2,"index":6188}},{"kind":"Variable","span":{"file_name":"src\\main.rs","byte_start":470,"byte_end":471,"line_start":18,"line_end":18,"column_start":5,"column_end":6},"ref_id":{"krate":0,"index":4294967212}},{"kind":"Variable","span":{"file_name":"src\\main.rs","byte_start":492,"byte_end":493,"line_start":18,"line_end":18,"column_start":27,"column_end":28},"ref_id":{"krate":0,"index":4294967197}},{"kind":"Function","span":{"file_name":"src\\main.rs","byte_start":643,"byte_end":649,"line_start":23,"line_end":23,"column_start":43,"column_end":49},"ref_id":{"krate":2,"index":4361}},{"kind":"Function","span":{"file_name":"src\\main.rs","byte_start":621,"byte_end":629,"line_start":23,"line_end":23,"column_start":21,"column_end":29},"ref_id":{"krate":2,"index":3218}},{"kind":"Function","span":{"file_name":"src\\main.rs","byte_start":613,"byte_end":618,"line_start":23,"line_end":23,"column_start":13,"column_end":18},"ref_id":{"krate":2,"index":6188}},{"kind":"Variable","span":{"file_name":"src\\main.rs","byte_start":605,"byte_end":612,"line_start":23,"line_end":23,"column_start":5,"column_end":12},"ref_id":{"krate":0,"index":4294967177}},{"kind":"Variable","span":{"file_name":"src\\main.rs","byte_start":634,"byte_end":635,"line_start":23,"line_end":23,"column_start":34,"column_end":35},"ref_id":{"krate":0,"index":4294967168}},{"kind":"Variable","span":{"file_name":"src\\main.rs","byte_start":639,"byte_end":641,"line_start":23,"line_end":23,"column_start":39,"column_end":41},"ref_id":{"krate":0,"index":4294967185}},{"kind":"Function","span":{"file_name":"src\\main.rs","byte_start":738,"byte_end":743,"line_start":28,"line_end":28,"column_start":20,"column_end":25},"ref_id":{"krate":2,"index":6188}},{"kind":"Variable","span":{"file_name":"src\\main.rs","byte_start":733,"byte_end":737,"line_start":28,"line_end":28,"column_start":15,"column_end":19},"ref_id":{"krate":0,"index":4294967154}},{"kind":"Variable","span":{"file_name":"src\\main.rs","byte_start":756,"byte_end":761,"line_start":29,"line_end":29,"column_start":9,"column_end":14},"ref_id":{"krate":0,"index":4294967145}},{"kind":"Function","span":{"file_name":"src\\main.rs","byte_start":765,"byte_end":778,"line_start":29,"line_end":29,"column_start":18,"column_end":31},"ref_id":{"krate":0,"index":15}},{"kind":"Variable","span":{"file_name":"src\\main.rs","byte_start":779,"byte_end":781,"line_start":29,"line_end":29,"column_start":32,"column_end":34},"ref_id":{"krate":0,"index":4294967143}},{"kind":"Variable","span":{"file_name":"src\\main.rs","byte_start":794,"byte_end":799,"line_start":31,"line_end":31,"column_start":5,"column_end":10},"ref_id":{"krate":0,"index":4294967145}}],"macro_refs":[],"relations":[]}